decipher_sdk/__init__.py
decipher_sdk/decipher_sdk.py
decipher_sdk_fastapi-0.0.22.dist-info/METADATA
decipher_sdk_fastapi-0.0.22.dist-info/WHEEL
decipher_sdk_fastapi-0.0.22.dist-info/top_level.txt
decipher_sdk_fastapi-0.0.22.dist-info/RECORD
