Metadata-Version: 2.1
Name: decipher-sdk-fastapi
Version: 0.0.22
Summary: A FastAPI SDK for error monitoring and logging.
Author: Decipher AI
Author-email: help@getdecipher.com
Requires-Python: >=3.7
Requires-Dist: fastapi
Requires-Dist: requests
